{
	"name": "DF_ORGA_DUMMY",
	"properties": {
		"folder": {
			"name": "CORE_DUMMY_VALUES"
		},
		"type": "MappingDataFlow",
		"typeProperties": {
			"sources": [
				{
					"dataset": {
						"referenceName": "SRC_AZRSQL_ALL_LAYER_STRUCTURE",
						"type": "DatasetReference"
					},
					"name": "sourceCoreOrga"
				}
			],
			"sinks": [
				{
					"dataset": {
						"referenceName": "TRG_AZRSQL_CORE_DUMMY_ORGA",
						"type": "DatasetReference"
					},
					"name": "sink1"
				}
			],
			"transformations": [
				{
					"name": "DerivedColumn1"
				},
				{
					"name": "OrderCol"
				}
			],
			"script": "source(output(\n\t\tCORG_DIM_ORGA_SK as string,\n\t\tCORG_MANDT as string,\n\t\tCORG_VKORG as string,\n\t\tCORG_VTWEG as string,\n\t\tCORG_KOKRS as string,\n\t\tCORG_BUKRS as string,\n\t\tCORG_SPRAS as string,\n\t\tCORG_BUTXT as string,\n\t\tCORG_ORT01 as string,\n\t\tCORG_LAND1 as string,\n\t\tCORG_VKORG_VTEXT as string,\n\t\tCORG_VTWEG_VTEXT as string,\n\t\tCORG_KOKRS_BEZEI as string,\n\t\tCORG_HASHKEY_BK as string,\n\t\tCORG_HASHKEY_DATA as string,\n\t\tCORG_CREATED_ON as string,\n\t\tCORG_SOURCE as string,\n\t\tCORG_VALID_FROM as string,\n\t\tCORG_VALID_TO as string,\n\t\tCORG_CURRENT_FLAG as string,\n\t\tCORG_DML_STRAT as string\n\t),\n\tallowSchemaDrift: true,\n\tvalidateSchema: false,\n\tisolationLevel: 'READ_UNCOMMITTED',\n\tquery: 'SELECT * FROM CORE.DIM_ORGA',\n\tformat: 'query') ~> sourceCoreOrga\nsourceCoreOrga derive(CORG_DIM_ORGA_SK = 0,\n\t\tCORG_MANDT = toInteger(CORG_MANDT),\n\t\tCORG_VKORG = 'DUMMY',\n\t\tCORG_VTWEG = 'DUMMY',\n\t\tCORG_KOKRS = 'DUMMY',\n\t\tCORG_BUKRS = 'DUMMY',\n\t\tCORG_SPRAS = 'DUMMY',\n\t\tCORG_BUTXT = 'DUMMY',\n\t\tCORG_ORT01 = 'DUMMY',\n\t\tCORG_LAND1 = 'DUMMY',\n\t\tCORG_VKORG_VTEXT = 'DUMMY',\n\t\tCORG_VTWEG_VTEXT = 'DUMMY',\n\t\tCORG_KOKRS_BEZEI = 'DUMMY',\n\t\tCORG_HASHKEY_BK = 'DUMMY',\n\t\tCORG_HASHKEY_DATA = 'DUMMY',\n\t\tCORG_CREATED_ON = toDate('29991231 00:00:00.0000000'),\n\t\tCORG_SOURCE = 'DUMMY',\n\t\tCORG_VALID_FROM = toDate('29991231 00:00:00.0000000'),\n\t\tCORG_VALID_TO = toDate('29991231 00:00:00.0000000'),\n\t\tCORG_CURRENT_FLAG = 'DUMMY',\n\t\tCORG_DML_STRAT = 'DUMMY') ~> DerivedColumn1\nDerivedColumn1 select(mapColumn(\n\t\tCORG_DIM_ORGA_SK,\n\t\tCORG_MANDT,\n\t\tCORG_VKORG,\n\t\tCORG_VTWEG,\n\t\tCORG_KOKRS,\n\t\tCORG_BUKRS,\n\t\tCORG_SPRAS,\n\t\tCORG_BUTXT,\n\t\tCORG_ORT01,\n\t\tCORG_LAND1,\n\t\tCORG_VKORG_VTEXT,\n\t\tCORG_VTWEG_VTEXT,\n\t\tCORG_KOKRS_BEZEI,\n\t\tCORG_HASHKEY_BK,\n\t\tCORG_HASHKEY_DATA,\n\t\tCORG_CREATED_ON,\n\t\tCORG_SOURCE,\n\t\tCORG_VALID_FROM,\n\t\tCORG_VALID_TO,\n\t\tCORG_CURRENT_FLAG,\n\t\tCORG_DML_STRAT\n\t),\n\tskipDuplicateMapInputs: true,\n\tskipDuplicateMapOutputs: true) ~> OrderCol\nOrderCol sink(allowSchemaDrift: true,\n\tvalidateSchema: false,\n\tdeletable:false,\n\tinsertable:true,\n\tupdateable:false,\n\tupsertable:false,\n\tformat: 'table',\n\tpreSQLs:['TRUNCATE TABLE CORE.DIM_ORGA'],\n\tpostSQLs:['INSERT INTO [CORE].[DIM_ORGA]\\n           ([CORG_DIM_ORGA_SK]\\n           ,[CORG_MANDT]\\n           ,[CORG_VKORG]\\n           ,[CORG_VTWEG]\\n           ,[CORG_KOKRS]\\n           ,[CORG_BUKRS]\\n           ,[CORG_SPRAS]\\n           ,[CORG_BUTXT]\\n           ,[CORG_ORT01]\\n           ,[CORG_LAND1]\\n           ,[CORG_VKORG_VTEXT]\\n           ,[CORG_VTWEG_VTEXT]\\n           ,[CORG_KOKRS_BEZEI]\\n           ,[CORG_HASHKEY_BK]\\n           ,[CORG_HASHKEY_DATA]\\n           ,[CORG_CREATED_ON]\\n           ,[CORG_SOURCE]\\n           ,[CORG_VALID_FROM]\\n           ,[CORG_VALID_TO]\\n           ,[CORG_CURRENT_FLAG]\\n           ,[CORG_DML_STRAT])\\n     VALUES\\n           (0\\n           ,999\\n           ,\\'DUMMY\\'\\n           ,\\'DUMMY\\'\\n           ,\\'DUMMY\\'\\n           ,\\'DUMMY\\'\\n           ,\\'DUMMY\\'\\n           ,\\'DUMMY\\'\\n           ,\\'DUMMY\\'\\n           ,\\'DUMMY\\'\\n           ,\\'DUMMY\\'\\n           ,\\'DUMMY\\'\\n           ,\\'DUMMY\\'\\n           ,\\'DUMMY\\'\\n           ,\\'DUMMY\\'\\n           ,\\'29991231 00:00:00.0000000\\'\\n           ,\\'DUMMY\\'\\n           ,\\'29991231 00:00:00.0000000\\'\\n           ,\\'29991231 00:00:00.0000000\\'\\n           ,\\'Y\\'\\n           ,\\'DUMMY\\')'],\n\tskipDuplicateMapInputs: true,\n\tskipDuplicateMapOutputs: true) ~> sink1"
		}
	}
}